{
  "$schema": "../gen/schemas/desktop-schema.json",
  "identifier": "default",
  "description": "Capability for all windows",
  "windows": ["main", "results", "settings", "plugin-popup"],
  "permissions": [
    "core:default",
    "core:event:allow-listen",
    "core:event:allow-emit",
    "core:window:allow-hide",
    "core:window:allow-show",
    "core:window:allow-set-focus",
    "core:window:allow-center",
    "core:window:allow-set-position",
    "opener:default",
    "global-shortcut:allow-register",
    "global-shortcut:allow-unregister",
    "global-shortcut:allow-is-registered",
    "shell:allow-open"
  ]
}
